data_pipeline/__init__.py
data_pipeline/_avro_payload.py
data_pipeline/_clog_writer.py
data_pipeline/_consumer_tick.py
data_pipeline/_encryption_helper.py
data_pipeline/_fast_uuid.py
data_pipeline/_kafka_producer.py
data_pipeline/_kafka_util.py
data_pipeline/_namespace_util.py
data_pipeline/_pooled_kafka_producer.py
data_pipeline/_position_data_tracker.py
data_pipeline/_producer_retry.py
data_pipeline/_retry_util.py
data_pipeline/base_consumer.py
data_pipeline/client.py
data_pipeline/config.py
data_pipeline/consumer.py
data_pipeline/consumer_source.py
data_pipeline/data_pipeline.py
data_pipeline/envelope.py
data_pipeline/environment_configs.py
data_pipeline/expected_frequency.py
data_pipeline/initialization_vector.py
data_pipeline/message.py
data_pipeline/message_type.py
data_pipeline/meta_attribute.py
data_pipeline/position_data.py
data_pipeline/producer.py
data_pipeline/publish_guarantee.py
data_pipeline/registrar.py
data_pipeline/schema_cache.py
data_pipeline/team.py
data_pipeline/zookeeper.py
data_pipeline/helpers/__init__.py
data_pipeline/helpers/decorators.py
data_pipeline/helpers/frozendict_json_encoder.py
data_pipeline/helpers/lists.py
data_pipeline/helpers/log.py
data_pipeline/helpers/priority_refresh_queue.py
data_pipeline/helpers/singleton.py
data_pipeline/helpers/yelp_avro_store.py
data_pipeline/schemas/envelope_v1.avsc
data_pipeline/schemas/initialization_vector_v1.avsc
data_pipeline/schemas/monitoring_message_v1.avsc
data_pipeline/schemas/registration_message_v1.avsc
data_pipeline/schematizer_clientlib/__init__.py
data_pipeline/schematizer_clientlib/schematizer.py
data_pipeline/schematizer_clientlib/models/__init__.py
data_pipeline/schematizer_clientlib/models/avro_schema.py
data_pipeline/schematizer_clientlib/models/avro_schema_element.py
data_pipeline/schematizer_clientlib/models/consumer_group.py
data_pipeline/schematizer_clientlib/models/consumer_group_data_source.py
data_pipeline-0.9.12.dist-info/DESCRIPTION.rst
data_pipeline-0.9.12.dist-info/METADATA
data_pipeline-0.9.12.dist-info/RECORD
data_pipeline-0.9.12.dist-info/WHEEL
data_pipeline-0.9.12.dist-info/metadata.json
data_pipeline-0.9.12.dist-info/top_level.txt
