Metadata-Version: 2.0
Name: data-pipeline
Version: 0.9.12
Summary: Provides an interface to consume and publish to data pipeline topics.
Home-page: https://github.com/Yelp/data_pipeline
Author: Justin Cunningham
Author-email: bam@yelp.com
License: UNKNOWN
Keywords: d,a,t,a,_,p,i,p,e,l,i,n,e
Platform: UNKNOWN
Classifier: Development Status :: 2 - Pre-Alpha
Classifier: Intended Audience :: Developers
Classifier: Natural Language :: English
Classifier: Programming Language :: Python :: 2
Classifier: Programming Language :: Python :: 2.7
Classifier: Programming Language :: Python :: 3
Classifier: Programming Language :: Python :: 3.3
Classifier: Programming Language :: Python :: 3.4
Classifier: Programming Language :: Python :: Implementation :: PyPy
Requires-Dist: PyStaticConfiguration (>=0.9.0)
Requires-Dist: bravado (<8.4.0,>=8.3.0)
Requires-Dist: cached-property (>=0.1.5)
Requires-Dist: cffi (>=1.1.2)
Requires-Dist: cryptography (<=1.3.4)
Requires-Dist: data-pipeline-avro-util (>=0.2.1)
Requires-Dist: enum34 (>=1.0.4)
Requires-Dist: frozendict (==0.5)
Requires-Dist: kafka-python (>0.9.4,<1.0.0)
Requires-Dist: kafka-utils (>0.3.3)
Requires-Dist: psutil (==4.2.0)
Requires-Dist: pycrypto (>=2.6.1)
Requires-Dist: pyopenssl (==16.0.0)
Requires-Dist: pyramid-zipkin (>=0.16.0)
Requires-Dist: simplejson (>=2.1.2)
Requires-Dist: swagger-zipkin (>=0.1.0)
Requires-Dist: yelp-avro (==1.9.2)
Requires-Dist: yelp-clog (==2.2.11)
Provides-Extra: internal
Requires-Dist: pysensu-yelp (>=0.2.3); extra == 'internal'
Requires-Dist: yelp-kafka (>=5.0.0); extra == 'internal'
Requires-Dist: yelp-servlib (>=4.3.0); extra == 'internal'
Provides-Extra: testing_helpers
Requires-Dist: docker-compose (==1.5.2); extra == 'testing_helpers'
Requires-Dist: docker-py (==1.6.0); extra == 'testing_helpers'
Requires-Dist: requests (<2.7); extra == 'testing_helpers'
Provides-Extra: tools
Requires-Dist: thriftpy (<0.2.0); extra == 'tools'
Requires-Dist: yelp-batch (>=0.19.4); extra == 'tools'
Requires-Dist: yelp-conn (>=7.0.0); extra == 'tools'
